cmsplugin_header_control/__init__.py
cmsplugin_header_control/admin.py
cmsplugin_header_control/cms_plugins.py
cmsplugin_header_control/models.py
cmsplugin_header_control/migrations/0001_initial.py
cmsplugin_header_control/migrations/__init__.py
cmsplugin_header_control/templates/header_control/plugin.html
cmsplugin_header_control-0.1.0.dist-info/DESCRIPTION.rst
cmsplugin_header_control-0.1.0.dist-info/METADATA
cmsplugin_header_control-0.1.0.dist-info/RECORD
cmsplugin_header_control-0.1.0.dist-info/WHEEL
cmsplugin_header_control-0.1.0.dist-info/metadata.json
cmsplugin_header_control-0.1.0.dist-info/top_level.txt
